xud-wizard/__init__.py
xud-wizard/__main__.py
xud-wizard/down.py
xud-wizard/shell.py
xud-wizard/status.py
xud-wizard/up.py
xud-wizard/utils.py
xud-wizard/rpc/__init__.py
xud-wizard/rpc/bitcoind.py
xud-wizard/rpc/exception.py
xud-wizard/rpc/geth.py
xud-wizard/rpc/lnd.py
xud-wizard/rpc/lnrpc_pb2.py
xud-wizard/rpc/lnrpc_pb2_grpc.py
xud-wizard/rpc/raiden.py
xud-wizard/rpc/xud.py
xud-wizard/rpc/xurpc_pb2.py
xud-wizard/rpc/xurpc_pb2_grpc.py
xudwizard/__init__.py
xudwizard/__main__.py
xudwizard/config.py
xudwizard/down.py
xudwizard/shell.py
xudwizard/status.py
xudwizard/up.py
xudwizard/utils.py
xudwizard/rpc/__init__.py
xudwizard/rpc/bitcoind.py
xudwizard/rpc/exception.py
xudwizard/rpc/geth.py
xudwizard/rpc/lnd.py
xudwizard/rpc/lnrpc_pb2.py
xudwizard/rpc/lnrpc_pb2_grpc.py
xudwizard/rpc/raiden.py
xudwizard/rpc/xud.py
xudwizard/rpc/xurpc_pb2.py
xudwizard/rpc/xurpc_pb2_grpc.py
xud_wizard-0.1.11.dist-info/METADATA
xud_wizard-0.1.11.dist-info/WHEEL
xud_wizard-0.1.11.dist-info/entry_points.txt
xud_wizard-0.1.11.dist-info/top_level.txt
xud_wizard-0.1.11.dist-info/RECORD
